Walimaker/API.py
Walimaker/__init__.py
Walimaker/camera.py
Walimaker/config.py
Walimaker/constraints.py
Walimaker/cursor.py
Walimaker/draw.py
Walimaker/draw_options.py
Walimaker/events.py
Walimaker/facilitate.py
Walimaker/game_object.py
Walimaker/music.py
Walimaker/physics.py
Walimaker/screen.py
Walimaker/settings.py
Walimaker/sprite.py
Walimaker/test.py
Walimaker/textbox.py
Walimaker/tiledmap.py
Walimaker/static/DialogBox.png
Walimaker/static/DialogBox1.png
Walimaker/static/DialogBox2.png
Walimaker/static/pymunk_logo_googlecode.png
Walimaker/static/simkai.ttf
Walimaker/static/simsun.ttc
WGameEngine-2023.8.2.dist-info/METADATA
WGameEngine-2023.8.2.dist-info/WHEEL
WGameEngine-2023.8.2.dist-info/top_level.txt
WGameEngine-2023.8.2.dist-info/RECORD
